skk/BingSiteAuth.xml
skk/__init__.py
skk/_site_server.py
skk/googled1d4050a5e980949.html
skk/index.html
skk/site.ico
skk/wechat_qr_code.jpg
skk/base95/README.md
skk/base95/__init__.py
skk/base95/_core.py
skk/miumapp/README.md
skk/miumapp/__init__.py
skk/miumapp/_core.py
skk/miumapp/demo.html
skk/miumapp/demo.py
skk/miumapp/demo_ui.png
skk/mongo/README.md
skk/mongo/__init__.py
skk/mongo/_core.py
skk/mysql/README.md
skk/mysql/__init__.py
skk/mysql/_core.py
skk/objdb/README.md
skk/objdb/__init__.py
skk/objdb/_core.py
skk/objdb/动态属性.png
skk/objdb/对象方法.png
skk/ollama/README.md
skk/ollama/__init__.py
skk/ollama/_chat.py
skk/ollama/_chat_models.py
skk/openai/README.md
skk/openai/__init__.py
skk/openai/_chat.py
skk/openai/_chat_model.py
skk/openai/_group_chat.py
skk/postgre/README.md
skk/postgre/__init__.py
skk/postgre/_core.py
skk/vtype/__init__.py
skk/vtype/_core.py
skk-2025.12.8.dist-info/licenses/LICENSE
skk-2025.12.8.dist-info/WHEEL
skk-2025.12.8.dist-info/METADATA
skk-2025.12.8.dist-info/RECORD
