Metadata-Version: 2.4
Name: skk
Version: 2025.12.8
Summary: 本项目封装了一些Python开发中常用的功能，帮助你更高效地开发应用。
Author-email: 许灿标 <canbiaoxu@outlook.com>
Requires-Python: >=3.12
Classifier: License :: OSI Approved :: Apache Software License
License-File: LICENSE
Requires-Dist: numpy
Requires-Dist: pymysql
Requires-Dist: aiomysql
Requires-Dist: pymongo
Requires-Dist: motor
Requires-Dist: tornado
Requires-Dist: openai
Requires-Dist: asyncpg
